binance/__init__.py
binance/async_client.py
binance/base_client.py
binance/client.py
binance/depthcache.py
binance/enums.py
binance/exceptions.py
binance/helpers.py
binance/streams.py
binance/threaded_stream.py
binance/ws/__init__.py
binance/ws/constants.py
binance/ws/depthcache.py
binance/ws/keepalive_websocket.py
binance/ws/reconnecting_websocket.py
binance/ws/streams.py
binance/ws/threaded_stream.py
binance/ws/websocket_api.py
python_binance-1.0.23.dist-info/LICENSE
python_binance-1.0.23.dist-info/METADATA
python_binance-1.0.23.dist-info/WHEEL
python_binance-1.0.23.dist-info/top_level.txt
python_binance-1.0.23.dist-info/RECORD
